lofar_opah/__init__.py
lofar_opah/_logging.py
lofar_opah/_version.py
lofar_opah/control_restapi/_decorators.py
lofar_opah/control_restapi/rest_server.py
lofar_opah/control_restapi/server.py
lofar_opah/control_restapi/handler/antenna_handler.py
lofar_opah/control_restapi/handler/antennafield_handler.py
lofar_opah/control_restapi/handler/business.py
lofar_opah/control_restapi/handler/station_handler.py
lofar_opah/grafana_rpc/grafana_api.py
lofar_opah/grafana_rpc/server.py
lofar_opah-0.0.20.dist-info/licenses/LICENSE
lofar_opah-0.0.20.dist-info/METADATA
lofar_opah-0.0.20.dist-info/WHEEL
lofar_opah-0.0.20.dist-info/entry_points.txt
lofar_opah-0.0.20.dist-info/top_level.txt
lofar_opah-0.0.20.dist-info/RECORD
