Metadata-Version: 2.4
Name: lofar-opah
Version: 0.0.20
Summary: LOFAR Monitoring & Control Components
Home-page: https://git.astron.nl/lofar2.0/opah
License: Apache License 2.0
Classifier: Development Status :: 3 - Alpha
Classifier: Environment :: Web Environment
Classifier: Intended Audience :: Developers
Classifier: Intended Audience :: Science/Research
Classifier: License :: OSI Approved :: Apache Software License
Classifier: Operating System :: OS Independent
Classifier: Programming Language :: Python
Classifier: Programming Language :: Python :: 3
Classifier: Programming Language :: Python :: 3 :: Only
Classifier: Programming Language :: Python :: 3.10
Classifier: Programming Language :: Python :: 3.11
Classifier: Programming Language :: Python :: 3.12
Classifier: Programming Language :: Python :: 3.13
Classifier: Topic :: System :: Networking
Classifier: Topic :: System :: Distributed Computing
Classifier: Topic :: Internet :: WWW/HTTP
Classifier: Topic :: Internet :: WWW/HTTP :: Dynamic Content
Classifier: Topic :: Scientific/Engineering
Classifier: Topic :: Scientific/Engineering :: Astronomy
Requires-Python: >=3.10
License-File: LICENSE
Requires-Dist: lofar-lotus>=0.0.5
Requires-Dist: lofar-sid>=1.0.16
Requires-Dist: logfmter
Requires-Dist: numpy
Requires-Dist: prometheus-client
Requires-Dist: grpcio
Requires-Dist: grpcio-reflection
Requires-Dist: grpcio-tools
Requires-Dist: flask
Requires-Dist: waitress
Requires-Dist: flask_cors
Requires-Dist: flasgger
Requires-Dist: types-flask-cors
Requires-Dist: types-waitress
Dynamic: license-file
